setup.py
CoroCron/Cron.py
CoroCron/Job.py
CoroCron/Timer.py
CoroCron/Weekdays.py
CoroCron/__init__.py
CoroCron.egg-info/PKG-INFO
CoroCron.egg-info/SOURCES.txt
CoroCron.egg-info/dependency_links.txt
CoroCron.egg-info/top_level.txt