Metadata-Version: 1.1
Name: CoroCron
Version: 0.1.4
Summary: A pythonic cron using asyncio
Home-page: https://github.com/FlyingKiwiBird/EsiPysi
Author: Flying Kiwi
Author-email: github@flyingkiwibird.com
License: MIT
Keywords: Cron asyncio schedule
Platform: UNKNOWN
Classifier: Development Status :: 3 - Alpha
Classifier: Intended Audience :: Developers
Classifier: Topic :: Utilities
Classifier: Programming Language :: Python
Classifier: Programming Language :: Python :: 3.3
Classifier: Programming Language :: Python :: 3.4
Classifier: Programming Language :: Python :: 3.5
Classifier: Programming Language :: Python :: 3.6
